cvmpy/__init__.py
cvmpy/_base.py
cvmpy/_grupos.py
cvmpy/_utils.py
cvmpy-0.1.3.dist-info/LICENSE
cvmpy-0.1.3.dist-info/METADATA
cvmpy-0.1.3.dist-info/WHEEL
cvmpy-0.1.3.dist-info/top_level.txt
cvmpy-0.1.3.dist-info/RECORD
