Metadata-Version: 2.2
Name: cvmpy
Version: 0.1.3
Summary: Package to read and process data from the CVM website.
Home-page: https://github.com/drsansao/cvm
Author: Douglas Ricardo Sansao
Author-email: douglasrsansao@example.com
Classifier: Programming Language :: Python :: 3
Classifier: License :: OSI Approved :: MIT License
Classifier: Operating System :: OS Independent
Requires-Python: >=3.10.0
License-File: LICENSE
Requires-Dist: pandas>=2.2.3
Requires-Dist: numpy>=1.21.1
Requires-Dist: beautifulsoup4>=4.10.0
Dynamic: author
Dynamic: author-email
Dynamic: classifier
Dynamic: description
Dynamic: description-content-type
Dynamic: home-page
Dynamic: requires-dist
Dynamic: requires-python
Dynamic: summary
